pxsstray/__init__.py
pxsstray/_version.py
pxsstray/main.py
pxsstray/trayMenu.py
pxsstray/images/cross.png
pxsstray-1.2.dist-info/LICENSE.txt
pxsstray-1.2.dist-info/METADATA
pxsstray-1.2.dist-info/WHEEL
pxsstray-1.2.dist-info/entry_points.txt
pxsstray-1.2.dist-info/top_level.txt
pxsstray-1.2.dist-info/RECORD
