Metadata-Version: 2.2
Name: pxsstray
Version: 1.2
Summary: A small utility that controls dpms and screensaver status from the tray
Author-email: Sam Coulter <sam.w.coulter@gmail.com>
Project-URL: Homepage, https://github.com/samwcoulter/pxsstray
Project-URL: Issues, https://github.com/samwcoulter/pxsstray/issues
Classifier: Development Status :: 2 - Pre-Alpha
Classifier: Programming Language :: Python :: 3
Classifier: Environment :: X11 Applications
Classifier: Topic :: Desktop Environment :: Screen Savers
Classifier: Topic :: Utilities
Requires-Python: >=3.12
License-File: LICENSE.txt
Requires-Dist: pyside6
Requires-Dist: python-xlib
